hutils/__init__.py
hutils/classes.py
hutils/data_types.py
hutils/decorators.py
hutils/schemas.py
hutils/shortcuts.py
hutils/unittest.py
hutils/validators.py
hutils/django/__init__.py
hutils/django/apis.py
hutils/django/databases.py
hutils/django/migrations.py
hutils/django/unittest.py
hutils-1.0.21.dist-info/LICENSE
hutils-1.0.21.dist-info/METADATA
hutils-1.0.21.dist-info/WHEEL
hutils-1.0.21.dist-info/top_level.txt
hutils-1.0.21.dist-info/RECORD
