Metadata-Version: 2.1
Name: hutils
Version: 1.0.21
Summary: a charming python web util-library
Home-page: https://github.com/zaihui/hutils/
Author: ZaiHui Dev
Author-email: llk@kezaihui.com
License: MIT License
Classifier: License :: OSI Approved :: MIT License
Classifier: Programming Language :: Python :: 3
Classifier: Programming Language :: Python :: 3.6
Classifier: Programming Language :: Python :: 3.7
Classifier: Programming Language :: Python :: 3.8
Classifier: Programming Language :: Python :: 3.9
License-File: LICENSE
